ecg_i2s/__init__.py
ecg_i2s/app.py
ecg_i2s/ecg.py
ecg_i2s/ecgnew.py
ecg_itos/__init__.py
ecg_itos/app.py
ecg_itos/ecg.py
ecg_itos-0.0.1.dist-info/METADATA
ecg_itos-0.0.1.dist-info/WHEEL
ecg_itos-0.0.1.dist-info/top_level.txt
ecg_itos-0.0.1.dist-info/RECORD
