Metadata-Version: 2.1
Name: ecg-itos
Version: 0.0.1
Summary: ecgitos123
Author: zou linzhuang
Author-email: zoulinzhuang2204@hnu.edu.cn
License: MIT License
Classifier: Programming Language :: Python :: 3
Classifier: License :: OSI Approved :: MIT License
Classifier: Operating System :: OS Independent
